symfem/__init__.py
symfem/basis_functions.py
symfem/basix_interface.py
symfem/caching.py
symfem/create.py
symfem/finite_element.py
symfem/functionals.py
symfem/functions.py
symfem/geometry.py
symfem/mappings.py
symfem/moments.py
symfem/piecewise_functions.py
symfem/plotting.py
symfem/py.typed
symfem/quadrature.py
symfem/references.py
symfem/symbols.py
symfem/utils.py
symfem/version.py
symfem/elements/__init__.py
symfem/elements/abf.py
symfem/elements/ac.py
symfem/elements/alfeld_sorokina.py
symfem/elements/argyris.py
symfem/elements/aw.py
symfem/elements/bddf.py
symfem/elements/bdfm.py
symfem/elements/bdm.py
symfem/elements/bell.py
symfem/elements/bernardi_raugel.py
symfem/elements/bernstein.py
symfem/elements/bfs.py
symfem/elements/bubble.py
symfem/elements/conforming_crouzeix_raviart.py
symfem/elements/crouzeix_raviart.py
symfem/elements/direct_serendipity.py
symfem/elements/dpc.py
symfem/elements/dual.py
symfem/elements/enriched_galerkin.py
symfem/elements/fortin_soulie.py
symfem/elements/gopalakrishnan_lederer_schoberl.py
symfem/elements/guzman_neilan.py
symfem/elements/hct.py
symfem/elements/hermite.py
symfem/elements/hhj.py
symfem/elements/huang_zhang.py
symfem/elements/kmv.py
symfem/elements/lagrange.py
symfem/elements/lagrange_prism.py
symfem/elements/lagrange_pyramid.py
symfem/elements/morley.py
symfem/elements/morley_wang_xu.py
symfem/elements/mtw.py
symfem/elements/nedelec.py
symfem/elements/nedelec_prism.py
symfem/elements/p1_iso_p2.py
symfem/elements/p1_macro.py
symfem/elements/q.py
symfem/elements/rannacher_turek.py
symfem/elements/regge.py
symfem/elements/rhct.py
symfem/elements/rt.py
symfem/elements/serendipity.py
symfem/elements/taylor.py
symfem/elements/tnt.py
symfem/elements/transition.py
symfem/elements/trimmed_serendipity.py
symfem/elements/vector_enriched_galerkin.py
symfem/elements/wu_xu.py
symfem/polynomials/__init__.py
symfem/polynomials/degree_computation.py
symfem/polynomials/dual.py
symfem/polynomials/jacobi.py
symfem-2025.11.1.dist-info/licenses/LICENSE
symfem-2025.11.1.dist-info/WHEEL
symfem-2025.11.1.dist-info/METADATA
symfem-2025.11.1.dist-info/RECORD
