Metadata-Version: 2.4
Name: symfem
Version: 2025.11.1
Summary: a symbolic finite element definition library
Author-email: Matthew Scroggs <symfem@mscroggs.co.uk>
Requires-Python: >=3.10.0
License-File: LICENSE
Requires-Dist: sympy>=1.10
Requires-Dist: appdirs
Requires-Dist: sphinx ; extra == "docs"
Requires-Dist: sphinx-autoapi ; extra == "docs"
Requires-Dist: CairoSVG>=2.6.0 ; extra == "optional"
Requires-Dist: fenics-basix ; extra == "optional"
Requires-Dist: numpy ; extra == "optional"
Requires-Dist: fenics-ufl ; extra == "optional"
Requires-Dist: ruff ; extra == "style"
Requires-Dist: mypy ; extra == "style"
Requires-Dist: pytest ; extra == "test"
Requires-Dist: symfem[optional] ; extra == "test"
Project-URL: documentation, https://symfem.readthedocs.io/en/latest/
Project-URL: homepage, https://github.com/mscroggs/symfem
Project-URL: repository, https://github.com/mscroggs/symfem
Provides-Extra: docs
Provides-Extra: optional
Provides-Extra: style
Provides-Extra: test
